[
  {
    "id": "d-1043",
    "projectId": "p-1002",
    "projectTitle": "Community Solar Garden",
    "donorName": "Andrew Kiptoo",
    "donorEmail": "andrew.kiptoo@aol.com",
    "amount": 500,
    "message": "Go green!",
    "createdAt": "2025-10-15T12:07:47.651Z"
  },
  {
    "id": "d-1044",
    "projectId": "p-1002",
    "projectTitle": "Community Solar Garden",
    "donorName": "Margaret Kemunto",
    "donorEmail": "margaret.kemunto@aol.com",
    "amount": 350,
    "message": "",
    "createdAt": "2024-08-09T21:42:21.242Z"
  },
  {
    "id": "d-1045",
    "projectId": "p-1002",
    "projectTitle": "Community Solar Garden",
    "donorName": "James Kimani",
    "donorEmail": "james.kimani@yahoo.com",
    "amount": 200,
    "message": "Clean energy matters",
    "createdAt": "2023-07-04T18:32:12.990Z"
  },
  {
    "id": "d-1046",
    "projectId": "p-1002",
    "projectTitle": "Community Solar Garden",
    "donorName": "Mary Wanjiku",
    "donorEmail": "mary.wanjiku@icloud.com",
    "amount": 175,
    "message": "",
    "createdAt": "2025-08-10T01:26:17.501Z"
  },
  {
    "id": "d-1047",
    "projectId": "p-1002",
    "projectTitle": "Community Solar Garden",
    "donorName": "Andrew Kiptoo",
    "donorEmail": "andrew.kiptoo@mail.com",
    "amount": 300,
    "message": "For the environment",
    "createdAt": "2024-09-14T10:12:16.258Z"
  },
  {
    "id": "d-1048",
    "projectId": "p-1002",
    "projectTitle": "Community Solar Garden",
    "donorName": "Grace Achieng",
    "donorEmail": "grace.achieng@zoho.com",
    "amount": 125,
    "message": "",
    "createdAt": "2024-09-20T16:58:53.364Z"
  },
  {
    "id": "d-1049",
    "projectId": "p-1002",
    "projectTitle": "Community Solar Garden",
    "donorName": "George Odhiambo",
    "donorEmail": "george.odhiambo@gmail.com",
    "amount": 450,
    "message": "Solar power!",
    "createdAt": "2023-04-24T03:44:09.808Z"
  },
  {
    "id": "d-1050",
    "projectId": "p-1002",
    "projectTitle": "Community Solar Garden",
    "donorName": "Margaret Kemunto",
    "donorEmail": "margaret.kemunto@aol.com",
    "amount": 180,
    "message": "",
    "createdAt": "2026-11-30T17:01:05.514Z"
  },
  {
    "id": "d-1051",
    "projectId": "p-1002",
    "projectTitle": "Community Solar Garden",
    "donorName": "Peter Ochieng",
    "donorEmail": "peter.ochieng@aol.com",
    "amount": 250,
    "message": "Sustainable future",
    "createdAt": "2023-09-04T15:18:32.886Z"
  },
  {
    "id": "d-1052",
    "projectId": "p-1002",
    "projectTitle": "Community Solar Garden",
    "donorName": "Andrew Kiptoo",
    "donorEmail": "andrew.kiptoo@hotmail.com",
    "amount": 400,
    "message": "Third donation",
    "createdAt": "2024-02-18T21:19:41.515Z"
  },
  {
    "id": "d-1053",
    "projectId": "p-1002",
    "projectTitle": "Community Solar Garden",
    "donorName": "Mary Wanjiku",
    "donorEmail": "mary.wanjiku@icloud.com",
    "amount": 150,
    "message": "",
    "createdAt": "2026-05-13T12:07:33.760Z"
  },
  {
    "id": "d-1054",
    "projectId": "p-1002",
    "projectTitle": "Community Solar Garden",
    "donorName": "James Kimani",
    "donorEmail": "james.kimani@mail.com",
    "amount": 275,
    "message": "Green energy",
    "createdAt": "2023-10-16T21:16:57.514Z"
  },
  {
    "id": "d-1055",
    "projectId": "p-1002",
    "projectTitle": "Community Solar Garden",
    "donorName": "Anonymous",
    "donorEmail": "",
    "amount": 500,
    "message": "",
    "createdAt": "2024-04-06T20:57:21.570Z"
  },
  {
    "id": "d-1056",
    "projectId": "p-1002",
    "projectTitle": "Community Solar Garden",
    "donorName": "George Odhiambo",
    "donorEmail": "george.odhiambo@icloud.com",
    "amount": 190,
    "message": "Power to the people",
    "createdAt": "2024-01-22T00:40:15.668Z"
  },
  {
    "id": "d-1057",
    "projectId": "p-1002",
    "projectTitle": "Community Solar Garden",
    "donorName": "Margaret Kemunto",
    "donorEmail": "margaret.kemunto@hotmail.com",
    "amount": 225,
    "message": "",
    "createdAt": "2023-01-19T11:39:51.724Z"
  },
  {
    "id": "d-1058",
    "projectId": "p-1002",
    "projectTitle": "Community Solar Garden",
    "donorName": "Andrew Kiptoo",
    "donorEmail": "andrew.kiptoo@proton.me",
    "amount": 100,
    "message": "Every bit helps",
    "createdAt": "2024-06-19T20:21:50.057Z"
  },
  {
    "id": "d-1059",
    "projectId": "p-1002",
    "projectTitle": "Community Solar Garden",
    "donorName": "George Odhiambo",
    "donorEmail": "george.odhiambo@icloud.com",
    "amount": 300,
    "message": "Third donation",
    "createdAt": "2024-01-08T11:49:23.301Z"
  },
  {
    "id": "d-1060",
    "projectId": "p-1002",
    "projectTitle": "Community Solar Garden",
    "donorName": "Grace Achieng",
    "donorEmail": "grace.achieng@proton.me",
    "amount": 175,
    "message": "",
    "createdAt": "2025-10-20T16:55:50.993Z"
  },
  {
    "id": "d-1061",
    "projectId": "p-1002",
    "projectTitle": "Community Solar Garden",
    "donorName": "Peter Ochieng",
    "donorEmail": "peter.ochieng@icloud.com",
    "amount": 320,
    "message": "Solar future",
    "createdAt": "2025-05-31T19:00:05.722Z"
  },
  {
    "id": "d-1062",
    "projectId": "p-1002",
    "projectTitle": "Community Solar Garden",
    "donorName": "Mary Wanjiku",
    "donorEmail": "mary.wanjiku@outlook.com",
    "amount": 140,
    "message": "",
    "createdAt": "2024-07-09T01:18:29.901Z"
  },
  {
    "id": "d-1063",
    "projectId": "p-1002",
    "projectTitle": "Community Solar Garden",
    "donorName": "James Kimani",
    "donorEmail": "james.kimani@hotmail.com",
    "amount": 260,
    "message": "Clean energy",
    "createdAt": "2026-09-29T07:01:40.556Z"
  },
  {
    "id": "d-1064",
    "projectId": "p-1002",
    "projectTitle": "Community Solar Garden",
    "donorName": "Andrew Kiptoo",
    "donorEmail": "andrew.kiptoo@outlook.com",
    "amount": 185,
    "message": "",
    "createdAt": "2026-09-07T03:28:15.654Z"
  },
  {
    "id": "d-1065",
    "projectId": "p-1002",
    "projectTitle": "Community Solar Garden",
    "donorName": "George Odhiambo",
    "donorEmail": "george.odhiambo@mail.com",
    "amount": 210,
    "message": "Renewable energy!",
    "createdAt": "2025-04-14T18:23:01.932Z"
  },
  {
    "id": "d-1066",
    "projectId": "p-1002",
    "projectTitle": "Community Solar Garden",
    "donorName": "Margaret Kemunto",
    "donorEmail": "margaret.kemunto@mail.com",
    "amount": 280,
    "message": "Fourth time",
    "createdAt": "2023-02-07T08:49:53.450Z"
  },
  {
    "id": "d-1067",
    "projectId": "p-1002",
    "projectTitle": "Community Solar Garden",
    "donorName": "Peter Ochieng",
    "donorEmail": "peter.ochieng@outlook.com",
    "amount": 195,
    "message": "",
    "createdAt": "2025-03-01T12:13:14.664Z"
  },
  {
    "id": "d-1068",
    "projectId": "p-1002",
    "projectTitle": "Community Solar Garden",
    "donorName": "Andrew Kiptoo",
    "donorEmail": "andrew.kiptoo@icloud.com",
    "amount": 155,
    "message": "Go solar",
    "createdAt": "2026-10-23T00:41:14.198Z"
  },
  {
    "id": "d-1069",
    "projectId": "p-1002",
    "projectTitle": "Community Solar Garden",
    "donorName": "Grace Achieng",
    "donorEmail": "grace.achieng@mail.com",
    "amount": 230,
    "message": "",
    "createdAt": "2025-10-30T18:22:48.183Z"
  },
  {
    "id": "d-1070",
    "projectId": "p-1002",
    "projectTitle": "Community Solar Garden",
    "donorName": "Anonymous",
    "donorEmail": "",
    "amount": 400,
    "message": "Great initiative",
    "createdAt": "2026-04-07T04:27:53.997Z"
  },
  {
    "id": "d-1071",
    "projectId": "p-1002",
    "projectTitle": "Community Solar Garden",
    "donorName": "Mary Wanjiku",
    "donorEmail": "mary.wanjiku@outlook.com",
    "amount": 165,
    "message": "",
    "createdAt": "2025-04-04T01:40:06.847Z"
  },
  {
    "id": "d-1072",
    "projectId": "p-1002",
    "projectTitle": "Community Solar Garden",
    "donorName": "James Kimani",
    "donorEmail": "james.kimani@zoho.com",
    "amount": 240,
    "message": "For our children",
    "createdAt": "2023-03-14T21:46:57.560Z"
  },
  {
    "id": "d-1073",
    "projectId": "p-1002",
    "projectTitle": "Community Solar Garden",
    "donorName": "George Odhiambo",
    "donorEmail": "george.odhiambo@hotmail.com",
    "amount": 130,
    "message": "",
    "createdAt": "2024-11-02T10:04:08.004Z"
  },
  {
    "id": "d-1074",
    "projectId": "p-1002",
    "projectTitle": "Community Solar Garden",
    "donorName": "Andrew Kiptoo",
    "donorEmail": "andrew.kiptoo@zoho.com",
    "amount": 350,
    "message": "Seventh donation!",
    "createdAt": "2026-11-21T08:43:12.854Z"
  },
  {
    "id": "d-1075",
    "projectId": "p-1002",
    "projectTitle": "Community Solar Garden",
    "donorName": "Margaret Kemunto",
    "donorEmail": "margaret.kemunto@gmail.com",
    "amount": 175,
    "message": "",
    "createdAt": "2025-04-21T01:47:39.289Z"
  },
  {
    "id": "d-1076",
    "projectId": "p-1002",
    "projectTitle": "Community Solar Garden",
    "donorName": "Peter Ochieng",
    "donorEmail": "peter.ochieng@outlook.com",
    "amount": 290,
    "message": "Solar power",
    "createdAt": "2025-07-31T10:22:08.623Z"
  },
  {
    "id": "d-1077",
    "projectId": "p-1002",
    "projectTitle": "Community Solar Garden",
    "donorName": "Mary Wanjiku",
    "donorEmail": "mary.wanjiku@zoho.com",
    "amount": 145,
    "message": "",
    "createdAt": "2024-11-14T11:40:51.707Z"
  },
  {
    "id": "d-1078",
    "projectId": "p-1002",
    "projectTitle": "Community Solar Garden",
    "donorName": "Grace Achieng",
    "donorEmail": "grace.achieng@outlook.com",
    "amount": 200,
    "message": "Green future",
    "createdAt": "2025-11-19T11:25:37.509Z"
  },
  {
    "id": "d-1079",
    "projectId": "p-1002",
    "projectTitle": "Community Solar Garden",
    "donorName": "James Kimani",
    "donorEmail": "james.kimani@icloud.com",
    "amount": 170,
    "message": "",
    "createdAt": "2023-02-20T09:07:28.386Z"
  },
  {
    "id": "d-1080",
    "projectId": "p-1002",
    "projectTitle": "Community Solar Garden",
    "donorName": "George Odhiambo",
    "donorEmail": "george.odhiambo@aol.com",
    "amount": 250,
    "message": "Sixth donation",
    "createdAt": "2025-12-04T12:49:18.687Z"
  },
  {
    "id": "d-1081",
    "projectId": "p-1002",
    "projectTitle": "Community Solar Garden",
    "donorName": "Andrew Kiptoo",
    "donorEmail": "andrew.kiptoo@mail.com",
    "amount": 135,
    "message": "",
    "createdAt": "2025-12-15T00:42:08.102Z"
  },
  {
    "id": "d-1082",
    "projectId": "p-1002",
    "projectTitle": "Community Solar Garden",
    "donorName": "Margaret Kemunto",
    "donorEmail": "margaret.kemunto@icloud.com",
    "amount": 215,
    "message": "Clean energy",
    "createdAt": "2026-12-26T15:37:29.923Z"
  }
]