[
  {
    "id": "d-1001",
    "projectId": "p-1001",
    "projectTitle": "Neighborhood Learning Lab",
    "donorName": "James Kimani",
    "donorEmail": "james.kimani@email.com",
    "amount": 500,
    "message": "For the kids!",
    "createdAt": "2024-03-15T09:15:00Z"
  },
  {
    "id": "d-1002",
    "projectId": "p-1001",
    "projectTitle": "Neighborhood Learning Lab",
    "donorName": "Mary Wanjiku",
    "donorEmail": "mary.wanjiku@email.com",
    "amount": 250,
    "message": "Education matters",
    "createdAt": "2024-03-22T11:30:00Z"
  },
  {
    "id": "d-1003",
    "projectId": "p-1001",
    "projectTitle": "Neighborhood Learning Lab",
    "donorName": "Peter Ochieng",
    "donorEmail": "peter.ochieng@email.com",
    "amount": 150,
    "message": "",
    "createdAt": "2024-04-08T08:45:00Z"
  },
  {
    "id": "d-1004",
    "projectId": "p-1001",
    "projectTitle": "Neighborhood Learning Lab",
    "donorName": "Grace Achieng",
    "donorEmail": "grace.achieng@email.com",
    "amount": 300,
    "message": "Happy to help",
    "createdAt": "2024-04-19T14:20:00Z"
  },
  {
    "id": "d-1005",
    "projectId": "p-1001",
    "projectTitle": "Neighborhood Learning Lab",
    "donorName": "John Mutua",
    "donorEmail": "john.mutua@email.com",
    "amount": 100,
    "message": "",
    "createdAt": "2024-05-03T10:00:00Z"
  },
  {
    "id": "d-1006",
    "projectId": "p-1001",
    "projectTitle": "Neighborhood Learning Lab",
    "donorName": "Sarah Njeri",
    "donorEmail": "sarah.njeri@email.com",
    "amount": 200,
    "message": "Great initiative!",
    "createdAt": "2024-05-17T16:30:00Z"
  },
  {
    "id": "d-1007",
    "projectId": "p-1001",
    "projectTitle": "Neighborhood Learning Lab",
    "donorName": "James Kimani",
    "donorEmail": "james.kimani@email.com",
    "amount": 175,
    "message": "Second donation",
    "createdAt": "2024-06-02T09:00:00Z"
  },
  {
    "id": "d-1008",
    "projectId": "p-1001",
    "projectTitle": "Neighborhood Learning Lab",
    "donorName": "Lucy Wambui",
    "donorEmail": "lucy.wambui@email.com",
    "amount": 125,
    "message": "For future leaders",
    "createdAt": "2024-06-18T13:15:00Z"
  },
  {
    "id": "d-1009",
    "projectId": "p-1001",
    "projectTitle": "Neighborhood Learning Lab",
    "donorName": "Anonymous",
    "donorEmail": "",
    "amount": 400,
    "message": "",
    "createdAt": "2024-07-05T08:30:00Z"
  },
  {
    "id": "d-1010",
    "projectId": "p-1001",
    "projectTitle": "Neighborhood Learning Lab",
    "donorName": "Mary Wanjiku",
    "donorEmail": "mary.wanjiku@email.com",
    "amount": 180,
    "message": "Keep up the good work",
    "createdAt": "2024-07-21T15:45:00Z"
  },
  {
    "id": "d-1011",
    "projectId": "p-1001",
    "projectTitle": "Neighborhood Learning Lab",
    "donorName": "Faith Muthoni",
    "donorEmail": "faith.muthoni@email.com",
    "amount": 220,
    "message": "",
    "createdAt": "2024-08-09T10:20:00Z"
  },
  {
    "id": "d-1012",
    "projectId": "p-1001",
    "projectTitle": "Neighborhood Learning Lab",
    "donorName": "James Kimani",
    "donorEmail": "james.kimani@email.com",
    "amount": 300,
    "message": "Third donation!",
    "createdAt": "2024-08-25T14:00:00Z"
  },
  {
    "id": "d-1013",
    "projectId": "p-1001",
    "projectTitle": "Neighborhood Learning Lab",
    "donorName": "Peter Ochieng",
    "donorEmail": "peter.ochieng@email.com",
    "amount": 150,
    "message": "",
    "createdAt": "2024-09-11T09:30:00Z"
  },
  {
    "id": "d-1014",
    "projectId": "p-1001",
    "projectTitle": "Neighborhood Learning Lab",
    "donorName": "Grace Achieng",
    "donorEmail": "grace.achieng@email.com",
    "amount": 275,
    "message": "Invest in education",
    "createdAt": "2024-09-28T11:45:00Z"
  },
  {
    "id": "d-1015",
    "projectId": "p-1001",
    "projectTitle": "Neighborhood Learning Lab",
    "donorName": "Mary Wanjiku",
    "donorEmail": "mary.wanjiku@email.com",
    "amount": 100,
    "message": "",
    "createdAt": "2024-10-14T08:00:00Z"
  },
  {
    "id": "d-1016",
    "projectId": "p-1001",
    "projectTitle": "Neighborhood Learning Lab",
    "donorName": "Daniel Njoroge",
    "donorEmail": "daniel.njoroge@email.com",
    "amount": 350,
    "message": "For my neighborhood",
    "createdAt": "2024-10-30T16:20:00Z"
  },
  {
    "id": "d-1017",
    "projectId": "p-1001",
    "projectTitle": "Neighborhood Learning Lab",
    "donorName": "James Kimani",
    "donorEmail": "james.kimani@email.com",
    "amount": 200,
    "message": "Fourth time",
    "createdAt": "2024-11-15T10:10:00Z"
  },
  {
    "id": "d-1018",
    "projectId": "p-1001",
    "projectTitle": "Neighborhood Learning Lab",
    "donorName": "Peter Ochieng",
    "donorEmail": "peter.ochieng@email.com",
    "amount": 125,
    "message": "",
    "createdAt": "2024-12-02T14:30:00Z"
  },
  {
    "id": "d-1019",
    "projectId": "p-1001",
    "projectTitle": "Neighborhood Learning Lab",
    "donorName": "Grace Achieng",
    "donorEmail": "grace.achieng@email.com",
    "amount": 175,
    "message": "Support local learning",
    "createdAt": "2024-12-19T09:15:00Z"
  },
  {
    "id": "d-1020",
    "projectId": "p-1001",
    "projectTitle": "Neighborhood Learning Lab",
    "donorName": "Joseph Wekesa",
    "donorEmail": "joseph.wekesa@email.com",
    "amount": 250,
    "message": "",
    "createdAt": "2025-01-07T13:40:00Z"
  },
  {
    "id": "d-1021",
    "projectId": "p-1001",
    "projectTitle": "Neighborhood Learning Lab",
    "donorName": "Anonymous",
    "donorEmail": "",
    "amount": 300,
    "message": "God bless",
    "createdAt": "2025-01-24T08:25:00Z"
  },
  {
    "id": "d-1022",
    "projectId": "p-1001",
    "projectTitle": "Neighborhood Learning Lab",
    "donorName": "Mary Wanjiku",
    "donorEmail": "mary.wanjiku@email.com",
    "amount": 100,
    "message": "",
    "createdAt": "2025-02-10T15:50:00Z"
  },
  {
    "id": "d-1023",
    "projectId": "p-1001",
    "projectTitle": "Neighborhood Learning Lab",
    "donorName": "Peter Ochieng",
    "donorEmail": "peter.ochieng@email.com",
    "amount": 200,
    "message": "Keep going",
    "createdAt": "2025-02-27T10:30:00Z"
  },
  {
    "id": "d-1024",
    "projectId": "p-1001",
    "projectTitle": "Neighborhood Learning Lab",
    "donorName": "James Kimani",
    "donorEmail": "james.kimani@email.com",
    "amount": 180,
    "message": "",
    "createdAt": "2025-03-16T14:15:00Z"
  },
  {
    "id": "d-1025",
    "projectId": "p-1001",
    "projectTitle": "Neighborhood Learning Lab",
    "donorName": "Samuel Karanja",
    "donorEmail": "samuel.karanja@email.com",
    "amount": 150,
    "message": "For the community",
    "createdAt": "2025-04-03T09:00:00Z"
  },
  {
    "id": "d-1026",
    "projectId": "p-1001",
    "projectTitle": "Neighborhood Learning Lab",
    "donorName": "Grace Achieng",
    "donorEmail": "grace.achieng@email.com",
    "amount": 250,
    "message": "Fifth donation",
    "createdAt": "2025-04-20T16:45:00Z"
  },
  {
    "id": "d-1027",
    "projectId": "p-1001",
    "projectTitle": "Neighborhood Learning Lab",
    "donorName": "Mary Wanjiku",
    "donorEmail": "mary.wanjiku@email.com",
    "amount": 100,
    "message": "",
    "createdAt": "2025-05-08T08:20:00Z"
  },
  {
    "id": "d-1028",
    "projectId": "p-1001",
    "projectTitle": "Neighborhood Learning Lab",
    "donorName": "Agnes Chebet",
    "donorEmail": "agnes.chebet@email.com",
    "amount": 225,
    "message": "Education first",
    "createdAt": "2025-05-25T12:30:00Z"
  },
  {
    "id": "d-1029",
    "projectId": "p-1001",
    "projectTitle": "Neighborhood Learning Lab",
    "donorName": "James Kimani",
    "donorEmail": "james.kimani@email.com",
    "amount": 175,
    "message": "",
    "createdAt": "2025-06-12T10:45:00Z"
  },
  {
    "id": "d-1030",
    "projectId": "p-1001",
    "projectTitle": "Neighborhood Learning Lab",
    "donorName": "Nancy Wangari",
    "donorEmail": "nancy.wangari@email.com",
    "amount": 120,
    "message": "Small help",
    "createdAt": "2025-06-29T15:00:00Z"
  },
  {
    "id": "d-1031",
    "projectId": "p-1001",
    "projectTitle": "Neighborhood Learning Lab",
    "donorName": "Peter Ochieng",
    "donorEmail": "peter.ochieng@email.com",
    "amount": 200,
    "message": "Fifth time!",
    "createdAt": "2025-07-17T09:30:00Z"
  },
  {
    "id": "d-1032",
    "projectId": "p-1001",
    "projectTitle": "Neighborhood Learning Lab",
    "donorName": "Mary Wanjiku",
    "donorEmail": "mary.wanjiku@email.com",
    "amount": 100,
    "message": "",
    "createdAt": "2025-08-04T14:20:00Z"
  },
  {
    "id": "d-1033",
    "projectId": "p-1001",
    "projectTitle": "Neighborhood Learning Lab",
    "donorName": "Anonymous",
    "donorEmail": "",
    "amount": 150,
    "message": "",
    "createdAt": "2025-08-22T08:15:00Z"
  },
  {
    "id": "d-1034",
    "projectId": "p-1001",
    "projectTitle": "Neighborhood Learning Lab",
    "donorName": "James Kimani",
    "donorEmail": "james.kimani@email.com",
    "amount": 80,
    "message": "Every bit counts",
    "createdAt": "2025-09-09T11:40:00Z"
  },
  {
    "id": "d-1035",
    "projectId": "p-1001",
    "projectTitle": "Neighborhood Learning Lab",
    "donorName": "Grace Achieng",
    "donorEmail": "grace.achieng@email.com",
    "amount": 190,
    "message": "",
    "createdAt": "2025-09-26T10:00:00Z"
  },
  {
    "id": "d-1036",
    "projectId": "p-1001",
    "projectTitle": "Neighborhood Learning Lab",
    "donorName": "Peter Ochieng",
    "donorEmail": "peter.ochieng@email.com",
    "amount": 145,
    "message": "Proud to support",
    "createdAt": "2025-10-14T15:30:00Z"
  },
  {
    "id": "d-1037",
    "projectId": "p-1001",
    "projectTitle": "Neighborhood Learning Lab",
    "donorName": "Mary Wanjiku",
    "donorEmail": "mary.wanjiku@email.com",
    "amount": 110,
    "message": "",
    "createdAt": "2025-11-01T09:45:00Z"
  },
  {
    "id": "d-1038",
    "projectId": "p-1001",
    "projectTitle": "Neighborhood Learning Lab",
    "donorName": "James Kimani",
    "donorEmail": "james.kimani@email.com",
    "amount": 130,
    "message": "",
    "createdAt": "2025-11-19T13:55:00Z"
  },
  {
    "id": "d-1039",
    "projectId": "p-1001",
    "projectTitle": "Neighborhood Learning Lab",
    "donorName": "Victor Simiyu",
    "donorEmail": "victor.simiyu@email.com",
    "amount": 95,
    "message": "Good cause",
    "createdAt": "2025-12-07T08:30:00Z"
  },
  {
    "id": "d-1040",
    "projectId": "p-1001",
    "projectTitle": "Neighborhood Learning Lab",
    "donorName": "Peter Ochieng",
    "donorEmail": "peter.ochieng@email.com",
    "amount": 150,
    "message": "Seventh donation",
    "createdAt": "2025-12-24T16:10:00Z"
  },
  {
    "id": "d-1041",
    "projectId": "p-1001",
    "projectTitle": "Neighborhood Learning Lab",
    "donorName": "Mary Wanjiku",
    "donorEmail": "mary.wanjiku@email.com",
    "amount": 105,
    "message": "",
    "createdAt": "2026-01-10T10:25:00Z"
  },
  {
    "id": "d-1042",
    "projectId": "p-1001",
    "projectTitle": "Neighborhood Learning Lab",
    "donorName": "James Kimani",
    "donorEmail": "james.kimani@email.com",
    "amount": 95,
    "message": "Bless the children",
    "createdAt": "2026-01-22T14:40:00Z"
  }
]